{
  "$schema": "https://schema.management.azure.com/schemas/2019-04-01/deploymentTemplate.json#",
  "contentVersion": "1.0.0.0",
  "metadata": {
    "_generator": {
      "name": "AzOps"
    }
  },
  "parameters": {},
  "variables": {},
  "resources": [
    {
      "type": "Microsoft.Compute/virtualMachines",
      "name": "agustindev",
      "apiVersion": "2021-07-01",
      "location": "westus",
      "tags": null,
      "properties": {
        "vmId": "6a0ee310-c44e-470d-baf8-53b757e0ce29",
        "hardwareProfile": {
          "vmSize": "Standard_D2s_v3"
        },
        "storageProfile": {
          "imageReference": {
            "publisher": "MicrosoftWindowsDesktop",
            "offer": "Windows-10",
            "sku": "rs5-pro",
            "version": "latest",
            "exactVersion": "17763.1397.2008070242"
          },
          "osDisk": {
            "osType": "Windows",
            "name": "agustindev_OsDisk_1_59e9eb75206547eab5319c927b4e4340",
            "createOption": "FromImage",
            "caching": "ReadWrite",
            "managedDisk": {
              "storageAccountType": "Standard_LRS",
              "id": "/subscriptions/10ac26cd-10f5-4bdf-a172-4e959e9e861f/resourceGroups/AGUSTINDEV_GROUP/providers/Microsoft.Compute/disks/agustindev_OsDisk_1_59e9eb75206547eab5319c927b4e4340"
            },
            "diskSizeGB": 127
          },
          "dataDisks": []
        },
        "osProfile": {
          "computerName": "agustindev",
          "adminUsername": "agustin",
          "windowsConfiguration": {
            "provisionVMAgent": true,
            "enableAutomaticUpdates": true,
            "patchSettings": {
              "patchMode": "AutomaticByOS",
              "assessmentMode": "ImageDefault"
            }
          },
          "secrets": [],
          "allowExtensionOperations": true,
          "requireGuestProvisionSignal": true
        },
        "networkProfile": {
          "networkInterfaces": [
            {
              "id": "/subscriptions/10ac26cd-10f5-4bdf-a172-4e959e9e861f/resourceGroups/agustindev_group/providers/Microsoft.Network/networkInterfaces/agustindev689"
            }
          ]
        },
        "diagnosticsProfile": {
          "bootDiagnostics": {
            "enabled": true,
            "storageUri": "https://agustindevgroupdiag.blob.core.windows.net/"
          }
        },
        "licenseType": "Windows_Client"
      }
    }
  ],
  "outputs": {}
}
